picopg/__init__.py
picopg/connections.py
picopg/crud.py
picopg/models.py
picopg/partials.py
picopg/py.typed
picopg/sql_builder.py
picopg-0.1.11.dist-info/METADATA
picopg-0.1.11.dist-info/WHEEL
picopg-0.1.11.dist-info/entry_points.txt
picopg-0.1.11.dist-info/licenses/LICENSE
picopg-0.1.11.dist-info/RECORD
