Metadata-Version: 2.4
Name: picopg
Version: 0.1.11
Summary: A lightweight, Pydantic-powered micro ORM for interacting with PostgreSQL databases, inspired by SQLModel but without the SQLAlchemy dependency.
Project-URL: Homepage, https://github.com/camarin24/pico-pg
Project-URL: Repository, https://github.com/camarin24/pico-pg
Author-email: Cristian Marín <cm961224@gmail.com>
License: MIT
License-File: LICENSE
Classifier: Framework :: Pydantic
Classifier: Intended Audience :: Developers
Classifier: License :: OSI Approved :: MIT License
Classifier: Operating System :: OS Independent
Classifier: Programming Language :: Python :: 3.13
Classifier: Topic :: Database :: Database Engines/Servers
Classifier: Topic :: Software Development :: Libraries :: Python Modules
Requires-Python: >=3.13
Requires-Dist: psycopg[binary,pool]>=3.2.12
Requires-Dist: pydantic>=2.12.3
Provides-Extra: dev
Requires-Dist: pytest-asyncio>=0.21.0; extra == 'dev'
Requires-Dist: pytest>=7.4.0; extra == 'dev'
Requires-Dist: ruff>=0.14.2; extra == 'dev'
